{
  "$schema": "https://json-schema.org/draft/2020-12/schema",
  "title": "Ceraxia Planning Packet",
  "type": "object",
  "required": [
    "ok",
    "contract_version",
    "worker",
    "kind",
    "task",
    "roles_completed",
    "problem_statement",
    "task_triage",
    "repo_survey_request",
    "dependency_map",
    "work_breakdown",
    "design_options",
    "verification_strategy",
    "risk_register",
    "quality_bar",
    "acceptance_contract",
    "implementation_brief_blueprint",
    "planning_review_gate",
    "code_brigade_handoff",
    "next_action"
  ],
  "properties": {
    "ok": {"type": "boolean"},
    "contract_version": {"const": "eye-mechanicum.v1"},
    "worker": {"const": "PlanningBrigade"},
    "kind": {"const": "ceraxia_planning_packet"},
    "task": {"type": "string"},
    "roles_completed": {
      "type": "array",
      "items": {"type": "string"},
      "minItems": 5
    },
    "problem_statement": {"type": "object"},
    "task_triage": {"type": "object"},
    "repo_survey_request": {"type": "object"},
    "dependency_map": {"type": "object"},
    "work_breakdown": {"type": "object"},
    "design_options": {"type": "object"},
    "verification_strategy": {"type": "object"},
    "risk_register": {"type": "object"},
    "quality_bar": {"type": "object"},
    "acceptance_contract": {"type": "object"},
    "implementation_brief_blueprint": {"type": "object"},
    "planning_review_gate": {"type": "object"},
    "code_brigade_handoff": {"type": "object"},
    "next_action": {"type": "object"}
  }
}
